.DS_Store
methylprep/__init__.py
methylprep/__main__.py
methylprep/cli.py
methylprep/version.py
methylprep/download/__init__.py
methylprep/download/array_express.py
methylprep/download/geo.py
methylprep/download/geo_alert.py
methylprep/download/miniml.py
methylprep/download/process_data.py
methylprep/download/samplesheet_sync_idat.py
methylprep/files/__init__.py
methylprep/files/idat.py
methylprep/files/manifests.py
methylprep/files/sample_sheets.py
methylprep/models/__init__.py
methylprep/models/arrays.py
methylprep/models/controls.py
methylprep/models/meth_dataset.py
methylprep/models/probes.py
methylprep/models/qualityMask450.txt.gz
methylprep/models/qualityMaskEPIC.txt.gz
methylprep/models/qualityMaskEPICPLUS.txt.gz
methylprep/models/qualityMaskmouse.txt.gz
methylprep/models/raw_dataset.py
methylprep/models/samples.py
methylprep/models/sigset.py
methylprep/models/sketchy_probes.py
methylprep/processing/__init__.py
methylprep/processing/dye_bias.py
methylprep/processing/infer_channel_switch.py
methylprep/processing/load_processed.py
methylprep/processing/meth_dataset.py
methylprep/processing/multi_array_idat_batches.py
methylprep/processing/p_value_probe_detection.py
methylprep/processing/pipeline.py
methylprep/processing/postprocess.py
methylprep/processing/preprocess.py
methylprep/processing/raw_dataset.py
methylprep/processing/read_geo_processed.py
methylprep/utils/__init__.py
methylprep/utils/data_frames.py
methylprep/utils/files.py
methylprep/utils/parsing.py
methylprep/utils/progress_bar.py
methylprep-1.7.1.dist-info/LICENSE
methylprep-1.7.1.dist-info/METADATA
methylprep-1.7.1.dist-info/WHEEL
methylprep-1.7.1.dist-info/entry_points.txt
methylprep-1.7.1.dist-info/top_level.txt
methylprep-1.7.1.dist-info/RECORD
