Metadata-Version: 2.1
Name: methylprep
Version: 1.7.1
Summary: Python-based Illumina methylation array preprocessing software
Home-page: https://github.com/FOXOBioScience/methylprep
Author: Life Epigenetics
Author-email: info@FOXOBioScience.com
License: MIT
Project-URL: Documentation, https://life-epigenetics-methylprep.readthedocs-hosted.com/en/latest/
Project-URL: Source, https://github.com/FOXOBioScience/methylprep/
Project-URL: Funding, https://FOXOBioScience.com/
Keywords: methylation dna data processing epigenetics illumina
Platform: UNKNOWN
Classifier: Development Status :: 5 - Production/Stable
Classifier: Environment :: Console
Classifier: License :: OSI Approved :: MIT License
Classifier: Programming Language :: Python :: 3.7
Classifier: Topic :: Scientific/Engineering :: Bio-Informatics
Classifier: Topic :: Scientific/Engineering :: Medical Science Apps.
Classifier: Framework :: Jupyter
Classifier: Intended Audience :: Science/Research
Classifier: Intended Audience :: Financial and Insurance Industry
Classifier: Operating System :: MacOS :: MacOS X
Classifier: Operating System :: Microsoft :: Windows
Classifier: Operating System :: POSIX :: Linux
Requires-Dist: pyparsing (>3.0)
Requires-Dist: numpy
Requires-Dist: pandas (>=1.3.0)
Requires-Dist: scipy
Requires-Dist: statsmodels
Requires-Dist: tqdm
Requires-Dist: bs4
Requires-Dist: lxml
Requires-Dist: requests
Provides-Extra: dev
Requires-Dist: methylcheck ; extra == 'dev'
Requires-Dist: pytest ; extra == 'dev'
Requires-Dist: pytest-mock ; extra == 'dev'
Requires-Dist: matplotlib ; extra == 'dev'
Requires-Dist: scikit-learn ; extra == 'dev'
Requires-Dist: openpyxl ; extra == 'dev'
Requires-Dist: coverage ; extra == 'dev'
